partial_types/main.py
partial_types/mypy.py
partial_types-0.1.0.dist-info/licenses/LICENSE
partial_types-0.1.0.dist-info/METADATA
partial_types-0.1.0.dist-info/WHEEL
partial_types-0.1.0.dist-info/top_level.txt
partial_types-0.1.0.dist-info/RECORD
