Metadata-Version: 2.4
Name: partial-types
Version: 0.1.0
Summary: Add your description here
Author: FlorianNAdam
License-Expression: MIT
Requires-Python: >=3.13
License-File: LICENSE
Requires-Dist: pydantic>=2.11.7
Dynamic: license-file
